Metadata-Version: 1.1
Name: rds-create-cpu-alarms
Version: 1.6
Summary: AWS Cloudwatch RDS Tool for creating CPUUtilization Metric Alarms
Home-page: https://github.com/percolate/rds-create-cpu-alarms
Author: Mihailo Pavlisin
Author-email: mihailo@percolate.com
License: GPLv3
Keywords: aws rds2 rds cpu alarms cloudwatch boto
Platform: UNKNOWN
Classifier: Development Status :: 4 - Beta
Classifier: Environment :: Console
Classifier: Intended Audience :: System Administrators
Classifier: License :: OSI Approved :: GNU General Public License v3 (GPLv3)
Classifier: Natural Language :: English
Classifier: Operating System :: POSIX
Classifier: Programming Language :: Python
Classifier: Topic :: System :: Systems Administration
